tissuumaps/VERSION
tissuumaps/__init__.py
tissuumaps/__main__.py
tissuumaps/gui.py
tissuumaps/jupyter.py
tissuumaps/read_h5ad.py
tissuumaps/tarfile_stream.py
tissuumaps/views.py
tissuumaps/plugins/__init__.py
tissuumaps/static/favicon.ico
tissuumaps/static/css/style.css
tissuumaps/static/css/style.css.map
tissuumaps/static/js/flask.js
tissuumaps/static/js/index.html
tissuumaps/static/js/tmapp.js
tissuumaps/static/js/utils/HTMLElementUtils.js
tissuumaps/static/js/utils/OSDViewerUtils.js
tissuumaps/static/js/utils/customElementUtils.js
tissuumaps/static/js/utils/dataUtils.js
tissuumaps/static/js/utils/filterUtils.js
tissuumaps/static/js/utils/glUtils.js
tissuumaps/static/js/utils/h5Utils.js
tissuumaps/static/js/utils/h5Utils_worker.js
tissuumaps/static/js/utils/interfaceUtils.js
tissuumaps/static/js/utils/markerUtils.js
tissuumaps/static/js/utils/overlayUtils.js
tissuumaps/static/js/utils/pluginUtils.js
tissuumaps/static/js/utils/projectUtils.js
tissuumaps/static/js/utils/regionOperations.js
tissuumaps/static/js/utils/regionOperationsUI.js
tissuumaps/static/js/utils/regionUtils.js
tissuumaps/static/misc/difference.svg
tissuumaps/static/misc/favicon.ico
tissuumaps/static/misc/generate_sdf.py
tissuumaps/static/misc/intersection.svg
tissuumaps/static/misc/logo.svg
tissuumaps/static/misc/logo_40.png
tissuumaps/static/misc/markershapes.png
tissuumaps/static/misc/markershapes.svg
tissuumaps/static/misc/union.svg
tissuumaps/static/misc/uulogowhitetuum.png
tissuumaps/static/misc/uulogowhitetuumlogo.png
tissuumaps/static/misc/uulogowhitetuumlogo100.png
tissuumaps/static/misc/design/banner2.png
tissuumaps/static/misc/design/logo-github-2443-473.png
tissuumaps/static/misc/design/logo.png
tissuumaps/static/vendor/.gitignore
tissuumaps/static/vendor/CamanJS-4.1.2/dist/caman.full.js
tissuumaps/static/vendor/CamanJS-4.1.2/dist/caman.full.map
tissuumaps/static/vendor/CamanJS-4.1.2/dist/caman.full.min.js
tissuumaps/static/vendor/CamanJS-4.1.2/dist/caman.full.pack.js
tissuumaps-3.2.1.14.dist-info/licenses/LICENSE
tissuumaps-3.2.1.14.dist-info/METADATA
tissuumaps-3.2.1.14.dist-info/WHEEL
tissuumaps-3.2.1.14.dist-info/entry_points.txt
tissuumaps-3.2.1.14.dist-info/top_level.txt
tissuumaps-3.2.1.14.dist-info/RECORD
